madeira_tools/__init__.py
madeira_tools/base.py
madeira_tools/cloudfront_app.py
madeira_tools/cloudfront_site.py
madeira_tools/dispatch.py
madeira_tools/docker.py
madeira_tools/maintenance.py
madeira_tools/cf_templates/cloudfront_app.yml
madeira_tools/cf_templates/cloudfront_site.yml
madeira_tools-0.13.data/scripts/madeira-build-api
madeira_tools-0.13.data/scripts/madeira-build-ui
madeira_tools-0.13.data/scripts/madeira-clean-layers
madeira_tools-0.13.data/scripts/madeira-deploy
madeira_tools-0.13.data/scripts/madeira-package-layer
madeira_tools-0.13.data/scripts/madeira-remove
madeira_tools-0.13.data/scripts/madeira-run-api
madeira_tools-0.13.data/scripts/madeira-run-dev
madeira_tools-0.13.data/scripts/madeira-run-ui
madeira_tools-0.13.dist-info/METADATA
madeira_tools-0.13.dist-info/WHEEL
madeira_tools-0.13.dist-info/top_level.txt
madeira_tools-0.13.dist-info/RECORD
