Metadata-Version: 2.1
Name: madeira-tools
Version: 0.13
Summary: Madeira Tools
Home-page: https://github.com/mxmader/madeira-tools
Author: Joe Mader
Author-email: jmader@jmader.com
License: MIT
Classifier: License :: OSI Approved :: MIT License
Classifier: Programming Language :: Python :: 3
Classifier: Programming Language :: Python :: 3.8
Classifier: Programming Language :: Python :: 3.9
Requires-Dist: boto3
Requires-Dist: docopt
Requires-Dist: madeira
Requires-Dist: madeira-utils
Requires-Dist: requests
